{
  "sigil_id": "1d9d8566",
  "model": "kimi-k2.5:cloud",
  "generated_at": "2026-02-12T09:05:09.458563",
  "content": "**THE ARCHITECT'S SIGIL**  \n*Behavioral Signature: Analytical-Strategic Composite (ASC-Type 7)*\n\n---\n\n### **SIGIL STRUCTURE**\nA hexagonal mandala with six vertices representing behavioral dimensions, concentric rings indicating operational depth (Core \u2192 Surface), and a central vector arrow showing developmental trajectory.\n\n---\n\n### **DIMENSIONAL METRICS (0-1 Scale)**\n\n#### **1. COGNITIVE ARCHITECTURE (The Core Triad)**\n*Central triangle - the processing engine*\n- **Problem-Solving Velocity**: 0.87 (High computational speed with accuracy preference)\n- **Data Interpretation Precision**: 0.93 (Exceptional pattern recognition in structured datasets)\n- **Logical Reasoning Integrity**: 0.91 (Deductive > Inductive; syllogistic strength)\n- **Cognitive Load Capacity**: 0.84 (Sustains high complexity without degradation)\n\n#### **2. PROCESSING PATTERNS (The Methodological Ring)**\n*Inner hexagon - operational algorithms*\n- **Methodical Consistency**: 0.89 (Rigid adherence to sequential protocols)\n- **Evidence Threshold**: 0.92 (Requires >85% certainty for decision activation)\n- **Verification Frequency**: 0.86 (High recurrence of data-checking loops)\n- **Hypothesis Generation**: 0.64 (Conservative; favors validation over exploration)\n\n#### **3. ENVIRONMENTAL RESONANCE (The Contextual Field)**\n*First outer ring - situational fit*\n- **Structural Dependency**: 0.88 (Performance degrades 0.40 points in ambiguous contexts)\n- **Metric Clarity Requirement**: 0.85 (Requires quantifiable success indicators)\n- **Process Visibility**: 0.91 (Thrives with transparent systems and audit trails)\n- **Ambiguity Tolerance**: 0.18 (Significant discomfort with undefined variables)\n\n#### **4. BEHAVIORAL ATTRIBUTES (The Trait Constellation)**\n*Second outer ring - personality calibration*\n- **Detail Granularity**: 0.94 (Operates at sub-pixel resolution; 0.06 margin for error)\n- **Systematic Acquisition**: 0.87 (Learning follows hierarchical taxonomy)\n- **Risk Aversion Index**: 0.76 (Conservative; loss-prevention weighted)\n- **Error Sensitivity**: 0.83 (High anticipatory anxiety regarding mistakes)\n- **Completion Compulsion**: 0.79 (Strong drive for closure on open loops)\n\n#### **5. BEHAVIORAL TRAJECTORY (The Temporal Vector)**\n*Central arrow - directional momentum*\n- **Strategic Integration**: 0.68 (68% transition complete: task-focused \u2192 systems-thinking)\n- **Delegation Comfort**: 0.44 (Reluctant to release control over detail-precision)\n- **Meta-Cognitive Awareness**: 0.72 (Growing recognition of big-picture patterns)\n- **Tactical Retention**: 0.81 (Maintains hands-on capability while scaling upward)\n\n#### **6. EMOTIONAL REGULATION (The Baseline Stability)**\n*Background field - affective infrastructure*\n- **Affective Variance**: 0.08 (Minimal fluctuation; 0.92 stability coefficient)\n- **Stress Response Linearity**: 0.89 (Predictable, proportional reactions)\n- **Recovery Efficiency**: 0.85 (Rapid return to baseline post-disruption)\n- **Interference Resistance**: 0.77 (Emotional data rarely corrupts analytical processing)\n\n---\n\n### **OPERATIONAL SIGNATURE**\n**Primary Modality**: Evidence-Based Systematization  \n**Decision Latency**: 0.82 (Slower initial response due to verification requirements; high accuracy offset)  \n**Innovation Coefficient**: 0.34 (Improves existing systems > Creates novel frameworks)  \n**Collaboration Index**: 0.71 (Effective with defined roles; friction in unstructured teams)\n\n---\n\n### **ACTIVATION SEQUENCE**\n1. **Input**: Data ingestion (threshold: 0.75 completeness)\n2. **Processing**: Pattern matching \u2192 Logic verification \u2192 Risk assessment\n3. **Output**: Structured solution with error margins specified\n4. **Review**: Post-implementation audit (mandatory: 0.91 probability)\n\n**Critical Constraint**: Performance drops to 0.45 efficiency in environments lacking measurable outcomes or standardized procedures.\n\n**Optimization Vector**: Increase Strategic Integration to 0.85+ while maintaining Detail Granularity above 0.90.",
  "metrics": {
    "blt_compatibility": 1.0,
    "behavioral_richness": 1.0,
    "structural_validity": 1.0,
    "semantic_coherence": 1.0
  },
  "is_valid": true,
  "error": null
}